pytebis/__init__.py
pytebis/lazyloader.py
pytebis/tebis.py
pytebis-0.5.13.dist-info/LICENSE
pytebis-0.5.13.dist-info/METADATA
pytebis-0.5.13.dist-info/WHEEL
pytebis-0.5.13.dist-info/top_level.txt
pytebis-0.5.13.dist-info/RECORD
