Metadata-Version: 2.1
Name: pytebis
Version: 0.5.13
Summary: Python Connector for TeBIS from Steinhaus
Home-page: https://github.com/MrLight/pytebis
Author: MrLight
Author-email: mrlight1@gmx.de
License: mit
Keywords: Python,Connector,TeBIS,Steinhaus
Classifier: Development Status :: 4 - Beta
Classifier: Intended Audience :: Developers
Classifier: Topic :: Software Development :: Build Tools
Classifier: License :: OSI Approved :: MIT License
Classifier: Programming Language :: Python :: 3
Classifier: Programming Language :: Python :: 3.4
Classifier: Programming Language :: Python :: 3.5
Classifier: Programming Language :: Python :: 3.6
License-File: LICENSE
Requires-Dist: numpy
Requires-Dist: pandas
Requires-Dist: simplejson
